Metadata-Version: 2.1
Name: docklean
Version: 1.0.0b0
Summary: Tool to clean docker images and containers
Author: Muhammad Hashim
Author-email: hashim.muhammad9@gmail.com
